odoo8_addon_account_payment_transfer_reconcile_batch-8.0.1.0.0.99.dev8-py2.7-nspkg.pth
odoo8_addon_account_payment_transfer_reconcile_batch-8.0.1.0.0.99.dev8.dist-info/METADATA
odoo8_addon_account_payment_transfer_reconcile_batch-8.0.1.0.0.99.dev8.dist-info/RECORD
odoo8_addon_account_payment_transfer_reconcile_batch-8.0.1.0.0.99.dev8.dist-info/WHEEL
odoo8_addon_account_payment_transfer_reconcile_batch-8.0.1.0.0.99.dev8.dist-info/namespace_packages.txt
odoo8_addon_account_payment_transfer_reconcile_batch-8.0.1.0.0.99.dev8.dist-info/top_level.txt
odoo_addons/account_payment_transfer_reconcile_batch/README.rst
odoo_addons/account_payment_transfer_reconcile_batch/__init__.py
odoo_addons/account_payment_transfer_reconcile_batch/__openerp__.py
odoo_addons/account_payment_transfer_reconcile_batch/i18n/account_payment_transfer_reconcile_batch.pot
odoo_addons/account_payment_transfer_reconcile_batch/i18n/ca.po
odoo_addons/account_payment_transfer_reconcile_batch/i18n/de.po
odoo_addons/account_payment_transfer_reconcile_batch/i18n/es.po
odoo_addons/account_payment_transfer_reconcile_batch/i18n/fi.po
odoo_addons/account_payment_transfer_reconcile_batch/i18n/fr.po
odoo_addons/account_payment_transfer_reconcile_batch/i18n/it.po
odoo_addons/account_payment_transfer_reconcile_batch/i18n/nl.po
odoo_addons/account_payment_transfer_reconcile_batch/i18n/pt_BR.po
odoo_addons/account_payment_transfer_reconcile_batch/i18n/sl.po
odoo_addons/account_payment_transfer_reconcile_batch/models/__init__.py
odoo_addons/account_payment_transfer_reconcile_batch/models/payment_order.py
odoo_addons/account_payment_transfer_reconcile_batch/static/description/icon.png
odoo_addons/account_payment_transfer_reconcile_batch/tests/__init__.py
odoo_addons/account_payment_transfer_reconcile_batch/tests/test_account_payment_transfer_reconcile_batch.py
odoo_addons/account_payment_transfer_reconcile_batch/wizard/__init__.py
odoo_addons/account_payment_transfer_reconcile_batch/wizard/payment_order_create.py
